drf_pagination/__init__.py
drf_pagination/pagination.py
drf_pagination-1.0.0.dist-info/LICENSE
drf_pagination-1.0.0.dist-info/METADATA
drf_pagination-1.0.0.dist-info/WHEEL
drf_pagination-1.0.0.dist-info/RECORD
