Metadata-Version: 2.1
Name: drf_pagination
Version: 1.0.0
Summary: Django REST framework additional pagination
License: MIT
Author: cosmo
Author-email: xxiaocai@163.com
Requires-Python: >=3.12,<4.0
Classifier: License :: OSI Approved :: MIT License
Classifier: Programming Language :: Python :: 3
Classifier: Programming Language :: Python :: 3.12
Requires-Dist: djangorestframework (==3.6.2)
